optiverse/__init__.py
optiverse/config.py
optiverse/evaluator.py
optiverse/llm_client.py
optiverse/optimizer.py
optiverse/prompt_generator.py
optiverse/store.py
optiverse-0.0.2.dist-info/METADATA
optiverse-0.0.2.dist-info/WHEEL
optiverse-0.0.2.dist-info/top_level.txt
optiverse-0.0.2.dist-info/RECORD
