Metadata-Version: 2.4
Name: optiverse
Version: 0.0.2
Summary: Optimization framework using Large Language Models
Author-email: Mathieu Larose <mathieu@mathieularose.com>
License-Expression: GPL-3.0
Project-URL: Homepage, https://github.com/larose/optiverse
Project-URL: Repository, https://github.com/larose/optiverse
Classifier: Development Status :: 3 - Alpha
Classifier: Intended Audience :: Developers
Classifier: Operating System :: OS Independent
Classifier: Programming Language :: Python :: 3
Classifier: Programming Language :: Python :: 3.10
Classifier: Programming Language :: Python :: 3.11
Classifier: Programming Language :: Python :: 3.12
Requires-Python: >=3.10
Requires-Dist: openai==1.93.1
Provides-Extra: dev
Requires-Dist: black==25.1.0; extra == "dev"
Requires-Dist: build==1.2.2.post1; extra == "dev"
Requires-Dist: pyright==1.1.403; extra == "dev"
Requires-Dist: twine==6.1.0; extra == "dev"
